pyproximabe/__init__.py
pyproximabe/version.py
pyproximabe/core/__init__.py
pyproximabe/core/client.py
pyproximabe/core/handlers.py
pyproximabe/core/types.py
pyproximabe/proto/__init__.py
pyproximabe/proto/common_pb2.py
pyproximabe/proto/common_pb2_grpc.py
pyproximabe/proto/config_pb2.py
pyproximabe/proto/config_pb2_grpc.py
pyproximabe/proto/proxima_be_pb2.py
pyproximabe/proto/proxima_be_pb2_grpc.py
pyproximabe-0.2.dist-info/LICENSE
pyproximabe-0.2.dist-info/METADATA
pyproximabe-0.2.dist-info/WHEEL
pyproximabe-0.2.dist-info/top_level.txt
pyproximabe-0.2.dist-info/RECORD
